<?xml version="1.0" encoding="UTF-8"?>
<!DOCTYPE mapper PUBLIC "-//mybatis.org//DTD Mapper 3.0//EN" "http://mybatis.org/dtd/mybatis-3-mapper.dtd">
<mapper namespace="club.ljk.comm.dao.AuthorityMapper">
  <resultMap id="BaseResultMap" type="club.ljk.comm.model.Authority">
    <!--
      WARNING - @mbggenerated
      This element is automatically generated by MyBatis Generator, do not modify.
    -->
    <id column="authority_id" jdbcType="VARCHAR" property="authorityId" />
    <result column="authority_type" jdbcType="VARCHAR" property="authorityType" />
    <result column="authority_is_del" jdbcType="INTEGER" property="authorityIsDel" />
    <result column="authority_create" jdbcType="VARCHAR" property="authorityCreate" />
    <result column="authority_time" jdbcType="TIMESTAMP" property="authorityTime" />
  </resultMap>
  <sql id="Base_Column_List">
    <!--
      WARNING - @mbggenerated
      This element is automatically generated by MyBatis Generator, do not modify.
    -->
    authority_id, authority_type, authority_is_del, authority_create, authority_time
  </sql>
  <insert id="insertSelective" parameterType="club.ljk.comm.model.Authority">
    <!--
      WARNING - @mbggenerated
      This element is automatically generated by MyBatis Generator, do not modify.
    -->
    insert into xkey_authority
    <trim prefix="(" suffix=")" suffixOverrides=",">
      <if test="authorityId != null">
        authority_id,
      </if>
      <if test="authorityType != null">
        authority_type,
      </if>
      <if test="authorityIsDel != null">
        authority_is_del,
      </if>
      <if test="authorityCreate != null">
        authority_create,
      </if>
      <if test="authorityTime != null">
        authority_time,
      </if>
    </trim>
    <trim prefix="values (" suffix=")" suffixOverrides=",">
      <if test="authorityId != null">
        #{authorityId,jdbcType=VARCHAR},
      </if>
      <if test="authorityType != null">
        #{authorityType,jdbcType=VARCHAR},
      </if>
      <if test="authorityIsDel != null">
        #{authorityIsDel,jdbcType=INTEGER},
      </if>
      <if test="authorityCreate != null">
        #{authorityCreate,jdbcType=VARCHAR},
      </if>
      <if test="authorityTime != null">
        #{authorityTime,jdbcType=TIMESTAMP},
      </if>
    </trim>
  </insert>
  <update id="updateByPrimaryKeySelective" parameterType="club.ljk.comm.model.Authority">
    <!--
      WARNING - @mbggenerated
      This element is automatically generated by MyBatis Generator, do not modify.
    -->
    update xkey_authority
    <set>
      <if test="authorityType != null">
        authority_type = #{authorityType,jdbcType=VARCHAR},
      </if>
      <if test="authorityIsDel != null">
        authority_is_del = #{authorityIsDel,jdbcType=INTEGER},
      </if>
      <if test="authorityCreate != null">
        authority_create = #{authorityCreate,jdbcType=VARCHAR},
      </if>
      <if test="authorityTime != null">
        authority_time = #{authorityTime,jdbcType=TIMESTAMP},
      </if>
    </set>
    where authority_id = #{authorityId,jdbcType=VARCHAR}
  </update>
</mapper>